{"statuses":[{"value":"complete"},{"value":"notstarted"}],"overall":{"statuses":[{"status":"complete","count":81,"percentage":32.271},{"status":"notstarted","count":170,"percentage":67.729}],"totals":{"total":251}},"extra_fields":{},"goals":[{"goal":1,"statuses":[{"status":"complete","count":6,"percentage":46.154},{"status":"notstarted","count":7,"percentage":53.846}],"totals":{"total":13}},{"goal":2,"statuses":[{"status":"complete","count":3,"percentage":21.429},{"status":"notstarted","count":11,"percentage":78.571}],"totals":{"total":14}},{"goal":3,"statuses":[{"status":"complete","count":21,"percentage":75.0},{"status":"notstarted","count":7,"percentage":25.0}],"totals":{"total":28}},{"goal":4,"statuses":[{"status":"complete","count":9,"percentage":75.0},{"status":"notstarted","count":3,"percentage":25.0}],"totals":{"total":12}},{"goal":5,"statuses":[{"status":"complete","count":7,"percentage":43.75},{"status":"notstarted","count":9,"percentage":56.25}],"totals":{"total":16}},{"goal":6,"statuses":[{"status":"complete","count":2,"percentage":18.182},{"status":"notstarted","count":9,"percentage":81.818}],"totals":{"total":11}},{"goal":7,"statuses":[{"status":"complete","count":2,"percentage":33.333},{"status":"notstarted","count":4,"percentage":66.667}],"totals":{"total":6}},{"goal":8,"statuses":[{"status":"complete","count":9,"percentage":56.25},{"status":"notstarted","count":7,"percentage":43.75}],"totals":{"total":16}},{"goal":9,"statuses":[{"status":"complete","count":8,"percentage":66.667},{"status":"notstarted","count":4,"percentage":33.333}],"totals":{"total":12}},{"goal":10,"statuses":[{"status":"complete","count":3,"percentage":21.429},{"status":"notstarted","count":11,"percentage":78.571}],"totals":{"total":14}},{"goal":11,"statuses":[{"status":"complete","count":7,"percentage":46.667},{"status":"notstarted","count":8,"percentage":53.333}],"totals":{"total":15}},{"goal":12,"statuses":[{"status":"complete","count":3,"percentage":23.077},{"status":"notstarted","count":10,"percentage":76.923}],"totals":{"total":13}},{"goal":13,"statuses":[{"status":"complete","count":0,"percentage":0.0},{"status":"notstarted","count":8,"percentage":100.0}],"totals":{"total":8}},{"goal":14,"statuses":[{"status":"complete","count":0,"percentage":0.0},{"status":"notstarted","count":10,"percentage":100.0}],"totals":{"total":10}},{"goal":15,"statuses":[{"status":"complete","count":0,"percentage":0.0},{"status":"notstarted","count":14,"percentage":100.0}],"totals":{"total":14}},{"goal":16,"statuses":[{"status":"complete","count":0,"percentage":0.0},{"status":"notstarted","count":24,"percentage":100.0}],"totals":{"total":24}},{"goal":17,"statuses":[{"status":"complete","count":1,"percentage":4.0},{"status":"notstarted","count":24,"percentage":96.0}],"totals":{"total":25}}]}